lblimg2coords/__init__.py
lblimg2coords/convert.py
lblimg2coord-0.0.2.dist-info/LICENSE
lblimg2coord-0.0.2.dist-info/METADATA
lblimg2coord-0.0.2.dist-info/WHEEL
lblimg2coord-0.0.2.dist-info/entry_points.txt
lblimg2coord-0.0.2.dist-info/top_level.txt
lblimg2coord-0.0.2.dist-info/RECORD
